metaflow_extensions/card_notebook/plugins/cards/notebook/__init__.py
metaflow_card_notebook-1.0.8.dist-info/LICENSE
metaflow_card_notebook-1.0.8.dist-info/METADATA
metaflow_card_notebook-1.0.8.dist-info/WHEEL
metaflow_card_notebook-1.0.8.dist-info/top_level.txt
metaflow_card_notebook-1.0.8.dist-info/RECORD
