Metadata-Version: 2.1
Name: metaflow-card-notebook
Version: 1.0.8
Summary: Render Jupyter Notebooks in Metaflow Cards
Author: Hamel Husain
Author-email: hamel@outerbounds.com
License: Apache Software License 2.0
License-File: LICENSE
Requires-Dist: ipykernel (>=6.4.1)
Requires-Dist: papermill (>=2.3.3)
Requires-Dist: nbconvert (>=6.4.1)
Requires-Dist: nbformat (>=5.1.3)
Provides-Extra: dev
Requires-Dist: ipykernel (>=6.4.1) ; extra == 'dev'
Requires-Dist: papermill (>=2.3.3) ; extra == 'dev'
Requires-Dist: nbconvert (>=6.4.1) ; extra == 'dev'
Requires-Dist: nbformat (>=5.1.3) ; extra == 'dev'
Requires-Dist: metaflow ; extra == 'dev'
Requires-Dist: cogapp (==3.3.0) ; extra == 'dev'
